odoo/addons/account_invoice_mass_sending/README.rst
odoo/addons/account_invoice_mass_sending/__init__.py
odoo/addons/account_invoice_mass_sending/__manifest__.py
odoo/addons/account_invoice_mass_sending/data/queue_job.xml
odoo/addons/account_invoice_mass_sending/i18n/account_invoice_mass_sending.pot
odoo/addons/account_invoice_mass_sending/i18n/de.po
odoo/addons/account_invoice_mass_sending/i18n/es.po
odoo/addons/account_invoice_mass_sending/i18n/fr.po
odoo/addons/account_invoice_mass_sending/i18n/it.po
odoo/addons/account_invoice_mass_sending/models/__init__.py
odoo/addons/account_invoice_mass_sending/models/account_move.py
odoo/addons/account_invoice_mass_sending/readme/CONFIGURE.md
odoo/addons/account_invoice_mass_sending/readme/CONTRIBUTORS.md
odoo/addons/account_invoice_mass_sending/readme/DESCRIPTION.md
odoo/addons/account_invoice_mass_sending/readme/USAGE.md
odoo/addons/account_invoice_mass_sending/static/description/icon.png
odoo/addons/account_invoice_mass_sending/static/description/index.html
odoo/addons/account_invoice_mass_sending/tests/__init__.py
odoo/addons/account_invoice_mass_sending/tests/test_account_invoice_mass_sending.py
odoo/addons/account_invoice_mass_sending/views/account_invoice_views.xml
odoo/addons/account_invoice_mass_sending/wizards/__init__.py
odoo/addons/account_invoice_mass_sending/wizards/account_move_send.py
odoo/addons/account_invoice_mass_sending/wizards/account_move_send.xml
odoo_addon_account_invoice_mass_sending-17.0.1.0.0.2.dist-info/METADATA
odoo_addon_account_invoice_mass_sending-17.0.1.0.0.2.dist-info/WHEEL
odoo_addon_account_invoice_mass_sending-17.0.1.0.0.2.dist-info/top_level.txt
odoo_addon_account_invoice_mass_sending-17.0.1.0.0.2.dist-info/RECORD
