Metadata-Version: 2.1
Name: odoo-addon-account_invoice_mass_sending
Version: 17.0.1.0.0.2
Requires-Python: >=3.10
Requires-Dist: odoo-addon-queue_job>=17.0dev,<17.1dev
Requires-Dist: odoo>=17.0a,<17.1dev
Summary: This addon adds a mass sending feature on invoices.
Home-page: https://github.com/OCA/account-invoicing
License: AGPL-3
Author: =?utf-8?q?ACSONE_SA/NV=2C_Odoo_Community_Association_=28OCA=29=2C_Open_Net_S=C3=A0rl?=
Author-email: support@odoo-community.org
Classifier: Programming Language :: Python
Classifier: Framework :: Odoo
Classifier: Framework :: Odoo :: 17.0
Classifier: License :: OSI Approved :: GNU Affero General Public License v3
